pypen/__init__.py
pypen/__main__.py
pypen/pypen_template.py
pypen/settings.py
pypen/drawing/__init__.py
pypen/drawing/color.py
pypen/drawing/css_colors.py
pypen/drawing/fake_primitives.py
pypen/drawing/fake_pypen.py
pypen/drawing/pypen_class.py
pypen/drawing/pypen_window.py
pypen/resources/icon.png
pypen/utils/__init__.py
pypen/utils/helpers.py
pypen/utils/math.py
pypen-0.0.5.dist-info/AUTHORS
pypen-0.0.5.dist-info/LICENSE
pypen-0.0.5.dist-info/METADATA
pypen-0.0.5.dist-info/WHEEL
pypen-0.0.5.dist-info/entry_points.txt
pypen-0.0.5.dist-info/pbr.json
pypen-0.0.5.dist-info/top_level.txt
pypen-0.0.5.dist-info/RECORD
