Metadata-Version: 2.1
Name: pypen
Version: 0.0.5
Summary: Express your creativity in Python through simple PyPen sketches!
Home-page: https://github.com/Canvim/PyPen
Author: ErikWDev
Author-email: ErikWDev@gmail.com
License: MIT
Project-URL: Bug Tracker, https://github.com/Canvim/PyPen/issues/
Project-URL: Source Code, https://github.com/Canvim/PyPen/
Project-URL: Examples, https://github.com/Canvim/PyPen/tree/master/examples/
Platform: UNKNOWN
